twitter.common.concurrent-0.3.11-py2.7-nspkg.pth
twitter/common/concurrent/__init__.py
twitter/common/concurrent/deadline.py
twitter/common/concurrent/deferred.py
twitter/common/concurrent/event_muxer.py
twitter.common.concurrent-0.3.11.dist-info/DESCRIPTION.rst
twitter.common.concurrent-0.3.11.dist-info/METADATA
twitter.common.concurrent-0.3.11.dist-info/RECORD
twitter.common.concurrent-0.3.11.dist-info/WHEEL
twitter.common.concurrent-0.3.11.dist-info/metadata.json
twitter.common.concurrent-0.3.11.dist-info/namespace_packages.txt
twitter.common.concurrent-0.3.11.dist-info/top_level.txt
twitter.common.concurrent-0.3.11.dist-info/zip-safe
