Metadata-Version: 2.0
Name: twitter.common.concurrent
Version: 0.3.11
Summary: twitter.common basic concurrency utilities such as deadline() and defer().
Home-page: https://github.com/twitter/commons
Author: UNKNOWN
Author-email: UNKNOWN
License: Apache License, Version 2.0
Platform: UNKNOWN
Classifier: Intended Audience :: Developers
Classifier: License :: OSI Approved :: Apache Software License
Classifier: Operating System :: OS Independent
Classifier: Programming Language :: Python
Requires-Dist: futures (==2.2.0)
Requires-Dist: twitter.common.exceptions (==0.3.11)
Requires-Dist: twitter.common.lang (==0.3.11)
Requires-Dist: twitter.common.quantity (==0.3.11)
